athena_codegen/.env
athena_codegen/__init__.py
athena_codegen/apidev.py
athena_codegen/flow.py
athena_codegen/main.py
athena_codegen/requirements.txt
athena_codegen/prompt/__init__.py
athena_codegen/prompt/code_sys.py
athena_codegen/prompt/plan_sys.py
athena_codegen/tools/__init__.py
athena_codegen/tools/compile.py
athena_codegen/tools/globals.py
athena_codegen/tools/save_code.py
athena_codegen/tools/customagent/__init__.py
athena_codegen/tools/customagent/agentchat/__init__.py
athena_codegen/tools/customagent/agentchat/assistant_agent.py
athena_codegen/tools/customagent/agentchat/custom_conversable_agent.py
athena_codegen/tools/customagent/agentchat/groupchat.py
athena_codegen/tools/customagent/agentchat/user_proxy_agent.py
athena_codegen-1.0.0.dist-info/METADATA
athena_codegen-1.0.0.dist-info/WHEEL
athena_codegen-1.0.0.dist-info/top_level.txt
athena_codegen-1.0.0.dist-info/RECORD
